iso3166_scraper/__init__.py
iso3166_scraper/__main__.py
iso3166_scraper/extractor.py
iso3166_scraper/flag_mapper.py
iso3166_scraper/names.py
iso3166_scraper/retriever.py
iso3166_scraper/scraper.py
iso3166_scraper-0.0.1.dist-info/METADATA
iso3166_scraper-0.0.1.dist-info/WHEEL
iso3166_scraper-0.0.1.dist-info/entry_points.txt
iso3166_scraper-0.0.1.dist-info/top_level.txt
iso3166_scraper-0.0.1.dist-info/RECORD
