Metadata-Version: 2.1
Name: iso3166-scraper
Version: 0.0.1
Summary: A Python utility that scrapes ISO 3166 country code data from Wikipedia
Home-page: https://github.com/soulwing/iso3166-scraper
Author: Carl Harris
Author-email: ceharris414@gmail.com
Project-URL: Bug Tracker, https://github.com/soulwing/iso3166-scraper
Classifier: Programming Language :: Python :: 3
Classifier: License :: OSI Approved :: MIT License
Classifier: Operating System :: OS Independent
Requires-Python: >=3.9
Requires-Dist: beautifulsoup4
Requires-Dist: requests
Requires-Dist: ruamel.yaml
